PySortAlgos
