Metadata-Version: 2.1
Name: PySortAlgos
Version: 0.6
Summary: A simple package that contains some commonly used sorting functions
Home-page: https://github.com/your-username/PySortAlgos
Author: Bahir Hakimi
Author-email: bahirhakimy2020@gmail.com
Classifier: Development Status :: 3 - Alpha
Classifier: Intended Audience :: Developers
Classifier: Topic :: Software Development :: Build Tools
Classifier: License :: OSI Approved :: MIT License
Classifier: Programming Language :: Python :: 3.9
License-File: LICENSE
